i18/__init__.py
i18/cli.py
i18/grammars.py
i18/lexer.py
i18/parser.py
i18-1.0.6.dist-info/LICENSE.txt
i18-1.0.6.dist-info/METADATA
i18-1.0.6.dist-info/WHEEL
i18-1.0.6.dist-info/entry_points.txt
i18-1.0.6.dist-info/top_level.txt
i18-1.0.6.dist-info/RECORD
